{
  "id": "AMARNA_LETTERS",
  "names": {
    "ar": "رسائل تل العمارنة",
    "en": "Amarna letters",
    "alt_ar": [],
    "alt_en": []
  },
  "category": "",
  "period": {
    "ar": "",
    "en": "",
    "year_min": null,
    "year_max": null
  },
  "dynasty": {
    "ar": "",
    "en": ""
  },
  "material": [],
  "dimensions": {},
  "provenance": {
    "site_ar": "",
    "site_en": ""
  },
  "discovery": {
    "year": null,
    "by_ar": "",
    "by_en": ""
  },
  "current_location": {
    "museum_id": "BERLIN",
    "museum_ar": "المتحف الجديد ببرلين (متحف نفرتيتي)",
    "museum_en": "Neues Museum",
    "city_ar": "برلين",
    "city_en": "Berlin",
    "country": "Germany",
    "hall_id": "",
    "hall_ar": "",
    "hall_en": ""
  },
  "description": {
    "ar": "رسائل العمارنة (أو مسارد تل العمارنة أو أرشيف العمارنة) هي مجموعة كبيرة من الرُقم الطينية المكتوبة باللغة الأكادية (البابلية) والخط المسماري، وجدت في أرشيف قصر الملك المصري إخناتون (أمنحوتب الرابع) في مقر حكمه (أخت أتون) في تل العمارنة في مصر.\nتتكون الرسائل بشكل أساسي من مراسلات دبلوماسية بين الحكام المصريين وممثليهم في مملكتي كنعان وأمورو أو قادة المملكة المجاورة خلال عصر المملكة المصرية الحديثة بين 1360-1332 قبل الميلاد. عُثر على الرسائل في صعيد مصر في تل العمارنة (وهو الاسم الحديث للعاصمة المصرية القديمة التي أسسها الفرعون أخناتون (1350-130 قبل الميلاد) خلال عهد الأسرة الثامنة عشرة في مصر). اللغة التي كُتبت فيها رسائل العمارنة ليست لغة مألوفة التاريخ المصري، فقد كانت مكتوبة في الغالب بخط يُعرف باسم الأكادية المسمارية، وهو نظام الكتابة الذي كان منتشرًا في بلاد ما بين النهرين القديمة، وليس في مصر القديمة، وقد وُصفت اللغة المستخدمة في الكتابة أحيانًا بأنها لغة مختلطة من الكنعانية والأكادية. تمتد فترة المراسلات المكتوبة لحوالي ثلاثين عامًا. \nيبلغ مجموع الألواح المكتشفة 382 لوح طيني، منها 358 نشرها عالم الحضارة الآشورية النرويجي يورغين كنودتزون في كتابه ألواح تل العمارنة Die El-Amarna-Tafeln، والذي صدر في مجلدين (عامي 1907 و 1915) ولا يزال حتى اليوم يعتبر المرجع الشامل عن هذه الرسائل.\nتعتبر رسائل العمارنة ذات أهمية كبيرة للدراسات الكتابية وللسانيات السامية ، لأنها تسلط الضوء على ثقافة ولغة الشعوب الكنعانية في العصور التي سبقت المسيحية. فهذه الرسائل وعلى الرغم من كتابتها باللغة الأكادية فهي تشير إلى اللغة الأم لمن كتبوها والذين كانوا يتحدثون باللغة الكنعانيه في شكلها المبكر. حيث تعتبر الكنعانية هي اللغة التي انحدرت منها فيما بعد اللغة العبرية والفينيقية. تقدم اللغة «الكنعانية» الأولية صورة قيمة عن المرحلة الأولية لتلك اللغات قبل عدة قرون من ظهورها الفعلي الأول.  \n\n\n== قصة الاكتشاف ==\nفي عام 1885م قامت إحدى النسوة بالحفر في تلة العمارنة (التل الأثري لأخت أتون العتيقة) لاستخراج التربة من أجل صناعة الآجر الطيني، وخلال الحفر استخرجت بالصدفة بعض الرُقم المسمارية، لقد اعتقد الباحثون في البداية أن كسر هذه الرقم مزورة، لكنه تبين فيما بعد أنها حقيقية وهي تعرض مراسلات دبلوماسية من عدة ملوك موجهة للملك إخناتون، كثير من هذه المراسلات مصدرها ملوك قليلو الأهمية خضعوا لسياسة إخناتون والذي يمكن اعتباره أحد أشد الملوك الفراعنة رومانسية فقد تحدى سلطة الكهان وألحد بالمعبود الرسمى للبلاد (آمون) وفرض آتون كإله جديد وحاول إنشاء المدينة الفاضلة.\n\n\n== التنقيب ==\nخلال العامين 1891- 1892 م تمكن پتري (Flinders Petrie) من كشف الأرشيف الملكي في مدينة إخت أتون واكتشف المزيد من الرُقم، حيث وصل عددها المعروف منها 379 حتى اليوم، وقدمت معلومات عن الحلفاء الآسيويين للقصر الملكي. حيث أن أقدم الرسائل يعود لزمن أمنحوتب الثالث (1388- 1351 ق.م). والحديثة تعود لزمن اخناتون (1351- 1334 ق.م)، وكون الرٌقم كانت مغلفة ومصنفة بصناديق خشبية نجد أن أغلبها بلا تاريخ بعد اهتراء المغلف الخشبي وبالتالي يصعب سلسلتها زمنياً.\nكل الرسائل مكتوبة باللغة الأكادية عدا ثلاث رسائل، وأحياناً تظهر لهجة (لكنة) محلية لكتابها، فقد كانت اللغة الأكادية (البابلية) لغة التواصل العالمي كما أضحت عليه الآرامية بعدها، وكما اللاتينية في العصور الوسطى.\n\n\n== استنتاجات ==\nيمكن من خلال هذه الرسائل معرفة السياسة الخارجية لمصر في حينها، فكما تحوي رسائل الملوك الآسيوين كعمونيرا كذلك تحتوي نسخاً من الرسائل المرسلة من البلاط الملكي، بعض الرسائل بسيطة وسطحية منها ترج للملك أن يرسل ذهباً.\nيشير بعض الباحثين حول غرابة كون أرشيف القصر الملكي يتكون في معظمه من رسائل ملوك أغراب عن مصر وأمراء تابعين لها خارج حدودها، ويستنتج بعضهم مثل آلدرِد (Cyril Aldred) أن الملك المصري مارس سياسة خارجية بوعي مكنه من السيطرة على تلك الممالك والإمارات من خلال دعمه للملوك الضعفاء وإضعافه للملوك الأقوياء.\n\n\n== الرسائل ==\n\n\n== انظر أيضًا ==\nقائمة رسائل تل العمارنة.\nاستنساخ العالم النرويجي كوندتسون Jørgen Alexander Knudtzon في كتابه ألواح العمارنة مع مقدمة وشروحات Die El-Amarna-Tafeln, mit Einleitung und Erläuterungen لما مجموعه 358 نصًا من تل العمارنة على الرابط https://archive.org/details/dieelamarnatafel01knud/page/n4/mode/2up\n\n\n== مراجع ==\n\n\n== وصلات خارجية ==\nموسوعة رسائل تل العمارنة، مؤسسة كالفورنيا للدراسات القديمة",
    "en": "The Amarna letters (; sometimes referred to as the Amarna correspondence or Amarna tablets, and cited with the abbreviation \"EA\", for \"El Amarna\") are an archive, written on clay tablets, primarily consisting of diplomatic correspondence between the Egyptian administration and its representatives in Canaan and Amurru, or neighboring kingdom leaders, during the New Kingdom, spanning a period of no more than thirty years in the middle of the 14th century BC. The letters were found in Upper Egypt at el-Amarna, the modern name for the ancient Egyptian capital of Akhetaten, founded by pharaoh Akhenaten (c. 1351–1334 BC) during the Eighteenth Dynasty of Egypt.\nThe Amarna letters are unusual in Egyptological research, because they are written not in the language of ancient Egypt, but in cuneiform, the writing system of ancient Mesopotamia. Most are in a variety of Akkadian sometimes characterised as a mixed language, Canaanite-Akkadian; one especially long letter—abbreviated EA 24—was written in a late dialect of Hurrian, and is the longest contiguous text known to survive in that language.\nThe known tablets total 382 and fragments (350 are letters and the rest literary texts\nand school texts), of which 358 have been published by the Norwegian Assyriologist Jørgen Alexander Knudtzon in his work, Die El-Amarna-Tafeln, which came out in two volumes (1907 and 1915) and remains the standard edition to this day. The texts of the remaining 24 complete or fragmentary tablets excavated since Knudtzon have also been made available. Only 26 of the known tablets and fragments were found in their archaeological context, Building Q42.21.\nThe Amarna letters are of great significance for biblical studies as well as Semitic linguistics because they shed light on the culture and language of the Canaanite peoples in this time period. Though most are written in Akkadian, the Akkadian of the letters is heavily colored by the mother tongue of their writers, who probably spoke an early form of Proto-Canaanite, the language(s) which would later evolve into the mother languages of Hebrew and Phoenician. These \"Canaanisms\" provide valuable insights into the proto-stage of those languages several centuries prior to their first actual manifestation.\n\n\n== The letters ==\n\nThese letters, comprising cuneiform tablets written primarily in Akkadian—the regional language of diplomacy for this period—were first discovered around 1887 by local Egyptians who secretly dug most of them from the ruined city of Amarna, and sold them in the antiquities market. They had originally been stored in an ancient building that archaeologists have since called the Bureau of Correspondence of Pharaoh. Once the location where they were found was determined, the ruins were explored for more. The first archaeologist who successfully recovered more tablets was Flinders Petrie, who in 1891 and 1892 uncovered 21 fragments. Émile Chassinat, then director of the French Institute for Oriental Archaeology in Cairo, acquired two more tablets in 1903. Since Knudtzon's edition, some 24 more tablets, or fragments, have been found, either in Egypt, or identified in the collections of various museums.\nThe initial group of letters recovered by local Egyptians have been scattered among museums in Germany, the United Kingdom, Egypt, France, Russia, and the United States:\n\n202 or 203 tablets are at the Vorderasiatisches Museum in Berlin;\n99 are at the British Museum in London;\n49 or 50 are at the Egyptian Museum in Cairo;\n7 at the Louvre in Paris;\n3 at the Pushkin Museum in Moscow;\n1 in the collection of the Institute for the Study of Ancient Cultures in Chicago.\nA few tablets are at the Ashmolean Museum in Oxford and the Royal Museums of Art and History in Brussels.\nThe archive contains a wealth of information about cultures, kingdoms, events and individuals in a period from which few written sources survive. It includes correspondence from Akhenaten (also titled Amenhotep IV)'s reign, as well as his predecessor Amenhotep III's reign. The tablets consist of over 300 diplomatic letters; the remainder comprise miscellaneous literary and educational materials. These tablets shed much light on Egyptian relations with Babylonia, Assyria,  Syria, Canaan, and Alashiya (Cyprus) as well as relations with the Mitanni, and the Hittites. The letters have been important in establishing both the history and the chronology of the period. Letters from the Babylonian king, Kadashman-Enlil I, anchor the timeframe of Akhenaten's reign to the mid-14th century BC. They also contain the first mention of a Near Eastern group known as the Habiru, whose possible connection with the Hebrews—due to the similarity of the words and their geographic location—remains debated. Other rulers involved in the letters include Tushratta of Mitanni, Lib'ayu of Shechem, Abdi-Heba of Jerusalem, and the quarrelsome king, Rib-Hadda, of Byblos, who, in over 58 letters, continuously pleads for Egyptian military help. Specifically, the letters include requests for military help in the north against Hittite invaders, and in the south to fight against the Habiru.\n\n\n=== Letter found at Tell Beth-Shean ===\nDuring excavation in 1993 a small, damaged, clay cylinder (first thought to be a cylinder seal) was found. It was inscribed with \"Amarna Cuneiform\" and held a letter which appears to be part of the Amarna correspondence.\n\n\"To Lab'aya, my lord, speak. Message of Tagi: To the King (Pharaoh), my lord: \"I have listened carefully to your missive to me ...(illegible traces)\"\n\n\n=== Letter summary ===\n\nAmarna Letters are politically arranged in a rough counterclockwise fashion:\n\n001–014 Babylonia\n015–016 Assyria\n017–030 Mitanni\n031–032 Arzawa\n033–040 Alashiya\n041–044 Hatti\n045–380+ Syria/Lebanon/Canaan\nAmarna Letters from Syria/Lebanon/Canaan are distributed roughly:\n\n045–067 Syria\n068–227 Lebanon (where 68–140 are from Gubla aka Byblos)\n227–380 Canaan (written mostly in the Canaano-Akkadian language).\n\n\n=== Akhenaten and Tushratta ===\nEarly in his reign, Akhenaten, the pharaoh of Egypt, had conflicts with Tushratta, the king of Mitanni, who had courted favor with his father, Amenhotep III, against the Hittites. Tushratta complains in numerous letters that Akhenaten had sent him gold-plated statues rather than statues made of solid gold; the statues formed part of the bride-price that Tushratta received for letting his daughter Tadukhepa marry Amenhotep III and then later marry Akhenaten.\nAn Amarna letter preserves a complaint by Tushratta to Akhenaten about the situation:\n\nI...asked your father Mimmureya [i.e., Amenhotep III] for statues of solid cast gold, ... and your father said, 'Don't talk of giving statues just of solid cast gold. I will give you ones made also of lapis lazuli. I will give you too, along with the statues, much additional gold and [other] goods beyond measure.' Every one of my messengers that were staying in Egypt saw the gold for the statues with their own eyes. ... But my brother [i.e., Akhenaten] has not sent the solid [gold] statues that your father was going to send. You have sent plated ones of wood. Nor have you sent me the goods that your father was going to send me, but you have reduced [them] greatly. Yet there is nothing I know of in which I have failed my brother. ... May my brother send me much gold. ... In my brother's country gold is as plentiful as dust. May my brother cause me no distress. May he send me much gold in order that my brother [with the gold and m]any [good]s may honour me.\n\n\n=== Jerusalem and the Habiru threat ===\nA significant cluster of the Amarna letters (EA 285–290) was written by Abdi-Heba, the Canaanite chieftain of Jerusalem (referred to in the tablets as Urusalim).\nIn his correspondence, Abdi-Heba repeatedly pleads with the pharaoh—likely Akhenaten—for military assistance, specifically requesting archers to defend against the Habiru, a nomadic or semi-nomadic group of marauders and mercenaries who were attacking Egyptia",
    "ar_intro": "رسائل العمارنة  هي مجموعة كبيرة من الرُقم الطينية المكتوبة باللغة الأكادية (البابلية) والخط المسماري، وجدت في أرشيف قصر الملك المصري إخناتون في مقر حكمه في تل العمارنة في مصر.",
    "en_intro": "The Amarna letters are an archive, written on clay tablets, primarily consisting of diplomatic correspondence between the Egyptian administration and its representatives in Canaan and Amurru, or neighboring kingdom leaders, during the New Kingdom, spanning a period of no more than thirty years in the middle of the 14th century BC. The letters were found in Upper Egypt at el-Amarna, the modern name for the ancient Egyptian capital of Akhetaten, founded by pharaoh Akhenaten during the Eighteenth Dynasty of Egypt."
  },
  "images": [
    {
      "filename": "AMARNA_LETTERS_01.jpg",
      "source": "wikimedia_commons",
      "source_url": "https://commons.wikimedia.org/wiki/File:Five_Amarna_letters_on_display_at_the_British_Museum%2C_LondonA.jpg",
      "credit": "Osama Shukir Muhammed Amin FRCP(Glasg)",
      "license": "CC BY-SA 4.0",
      "license_url": "https://creativecommons.org/licenses/by-sa/4.0",
      "width": 3074,
      "height": 3004,
      "is_primary": true,
      "caption_en": "Five Amarna letters on display (G57/dc8) at the British Museum, London.",
      "object_name": "Five Amarna letters on display at the British Museum, LondonA",
      "original_filename": "Five_Amarna_letters_on_display_at_the_British_Museum,_LondonA.jpg"
    },
    {
      "filename": "AMARNA_LETTERS_02.jpg",
      "source": "wikimedia_commons",
      "source_url": "https://commons.wikimedia.org/wiki/File:Amarna_letter-_Royal_Letter_from_Ashur-uballit%2C_the_king_of_Assyria%2C_to_the_king_of_Egypt_MET_24.2.11_EGDP021806.jpg",
      "credit": "This file was donated to Wikimedia Commons as part of a project by the Metropolitan Museum of Art . See the Image and Data Resources Open Access Policy",
      "license": "CC0",
      "license_url": "http://creativecommons.org/publicdomain/zero/1.0/deed.en",
      "width": 3000,
      "height": 4000,
      "is_primary": false,
      "caption_en": "Tablet, Amarna letter",
      "object_name": "Amarna letter: Royal Letter from Ashur-uballit, the king of Assyria, to the king of Egypt",
      "original_filename": "Amarna_letter-_Royal_Letter_from_Ashur-uballit,_the_king_of_Assyria,_to_the_king_of_Egypt_MET_24.2.11_EGDP021806.jpg"
    },
    {
      "filename": "AMARNA_LETTERS_03.jpg",
      "source": "wikimedia_commons",
      "source_url": "https://commons.wikimedia.org/wiki/File:Amarna_letter-_Royal_Letter_from_Ashur-uballit%2C_the_king_of_Assyria%2C_to_the_king_of_Egypt_MET_DP-211-142.jpg",
      "credit": "This file was donated to Wikimedia Commons as part of a project by the Metropolitan Museum of Art . See the Image and Data Resources Open Access Policy",
      "license": "CC0",
      "license_url": "http://creativecommons.org/publicdomain/zero/1.0/deed.en",
      "width": 2181,
      "height": 2745,
      "is_primary": false,
      "caption_en": "Tablet, Amarna letter",
      "object_name": "Amarna letter: Royal Letter from Ashur-uballit, the king of Assyria, to the king of Egypt",
      "original_filename": "Amarna_letter-_Royal_Letter_from_Ashur-uballit,_the_king_of_Assyria,_to_the_king_of_Egypt_MET_DP-211-142.jpg"
    },
    {
      "filename": "AMARNA_LETTERS_04.jpg",
      "source": "wikimedia_commons",
      "source_url": "https://commons.wikimedia.org/wiki/File:Amarna_letter-_Royal_Letter_from_Ashur-uballit%2C_the_king_of_Assyria%2C_to_the_king_of_Egypt_MET_24.2.11_EGDP021805.jpg",
      "credit": "This file was donated to Wikimedia Commons as part of a project by the Metropolitan Museum of Art . See the Image and Data Resources Open Access Policy",
      "license": "CC0",
      "license_url": "http://creativecommons.org/publicdomain/zero/1.0/deed.en",
      "width": 3000,
      "height": 4000,
      "is_primary": false,
      "caption_en": "Tablet, Amarna letter",
      "object_name": "Amarna letter: Royal Letter from Ashur-uballit, the king of Assyria, to the king of Egypt",
      "original_filename": "Amarna_letter-_Royal_Letter_from_Ashur-uballit,_the_king_of_Assyria,_to_the_king_of_Egypt_MET_24.2.11_EGDP021805.jpg"
    },
    {
      "filename": "AMARNA_LETTERS_05.jpg",
      "source": "wikimedia_commons",
      "source_url": "https://commons.wikimedia.org/wiki/File:Amarna_letter-_Royal_Letter_from_Ashur-uballit%2C_the_king_of_Assyria%2C_to_the_king_of_Egypt_MET_24.2.11_EGDP021808.jpg",
      "credit": "This file was donated to Wikimedia Commons as part of a project by the Metropolitan Museum of Art . See the Image and Data Resources Open Access Policy",
      "license": "CC0",
      "license_url": "http://creativecommons.org/publicdomain/zero/1.0/deed.en",
      "width": 4000,
      "height": 3000,
      "is_primary": false,
      "caption_en": "Tablet, Amarna letter",
      "object_name": "Amarna letter: Royal Letter from Ashur-uballit, the king of Assyria, to the king of Egypt",
      "original_filename": "Amarna_letter-_Royal_Letter_from_Ashur-uballit,_the_king_of_Assyria,_to_the_king_of_Egypt_MET_24.2.11_EGDP021808.jpg"
    }
  ],
  "sources": [
    {
      "type": "wikipedia_en",
      "url": "https://en.wikipedia.org/wiki/Amarna_letters",
      "title": "Amarna letters",
      "license": "CC-BY-SA-4.0"
    },
    {
      "type": "wikipedia_ar",
      "url": "https://ar.wikipedia.org/wiki/%D8%B1%D8%B3%D8%A7%D8%A6%D9%84_%D8%AA%D9%84_%D8%A7%D9%84%D8%B9%D9%85%D8%A7%D8%B1%D9%86%D8%A9",
      "title": "رسائل تل العمارنة",
      "license": "CC-BY-SA-4.0"
    }
  ],
  "tags": [
    "14th-century bc literature",
    "1887 archaeological discoveries",
    "akkadian literature",
    "amarna",
    "amarna letters",
    "archaeological discoveries in egypt",
    "articles with short description",
    "commons category link from wikidata",
    "diplomatic correspondence",
    "egyptian inscriptions",
    "egyptian museum",
    "egyptological objects in the staatliche museen zu berlin",
    "extra-biblical references to canaan",
    "short description is different from wikidata",
    "webarchive template wayback links"
  ],
  "related_ids": [
    "KHUFU_SOLAR_BOAT",
    "PYRAMIDION_AMENEMHAT",
    "NEFERTITI_BUST",
    "BULL_PALETTE",
    "KHAFRE_ENTHRONED",
    "LIBYAN_PALETTE",
    "NARMER_PALETTE",
    "SEATED_SCRIBE"
  ],
  "qa_pairs_ar": [
    {
      "q": "ما هي رسائل تل العمارنة؟",
      "a": "رسائل العمارنة (أو مسارد تل العمارنة أو أرشيف العمارنة) هي مجموعة كبيرة من الرُقم الطينية المكتوبة باللغة الأكادية (البابلية) والخط المسماري، وجدت في أرشيف قصر الملك المصري إخناتون (أمنحوتب الرابع) في مقر حكمه (أخت أتون) في تل العمارنة في مصر.",
      "evidence": "description.ar_intro",
      "type": "identity"
    },
    {
      "q": "أين توجد رسائل تل العمارنة حاليًا؟",
      "a": "تُحفظ رسائل تل العمارنة في المتحف الجديد ببرلين (متحف نفرتيتي) في برلين.",
      "evidence": "current_location",
      "type": "location"
    },
    {
      "q": "اعطني نبذة عن رسائل تل العمارنة.",
      "a": "رسائل العمارنة (أو مسارد تل العمارنة أو أرشيف العمارنة) هي مجموعة كبيرة من الرُقم الطينية المكتوبة باللغة الأكادية (البابلية) والخط المسماري، وجدت في أرشيف قصر الملك المصري إخناتون (أمنحوتب الرابع) في مقر حكمه (أخت أتون) في تل العمارنة في مصر.\nتتكون الرسائل بشكل أساسي من مراسلات دبلوماسية بين الحكام المصريين وممثليهم في مملكتي كنعان وأمورو أو قادة المملكة المجاورة خلال عصر المملكة المصرية الحديثة بين 1360-1332 قبل الميلاد. عُثر على الرسائل في صعيد مصر في تل العمارنة (وهو الاسم الحديث للعاصمة المصرية القديمة التي أسسها الفرعون أخناتون (1350-130 قبل الميلاد) خلال عهد الأسرة الثامنة عشرة في مصر)....",
      "evidence": "description.ar",
      "type": "summary"
    }
  ],
  "highlight": true
}