{
  "id": "KHAFRE_ENTHRONED",
  "names": {
    "ar": "خفرع متوج",
    "en": "Khafre Enthroned",
    "alt_ar": [],
    "alt_en": []
  },
  "category": "",
  "period": {
    "ar": "",
    "en": "c. 2550 BC",
    "year_min": -2550,
    "year_max": -2550
  },
  "dynasty": {
    "ar": "",
    "en": ""
  },
  "material": [
    "Anorthosite gneiss"
  ],
  "dimensions": {
    "height": "1.68 meters"
  },
  "provenance": {
    "site_ar": "",
    "site_en": "Giza, Giza Governorate, Egypt"
  },
  "discovery": {
    "year": 1860,
    "by_ar": "",
    "by_en": "Auguste Mariette"
  },
  "current_location": {
    "museum_id": "EMC",
    "museum_ar": "المتحف المصري",
    "museum_en": "Egyptian Museum",
    "city_ar": "القاهرة",
    "city_en": "Cairo",
    "country": "Egypt",
    "hall_id": "",
    "hall_ar": "",
    "hall_en": ""
  },
  "description": {
    "ar": "خفرع متوج هو تمثال جنائزي للملك المصري خفرع، الذي حكم خلال الأسرة المصرية الرابعة (حوالي 2570 قبل الميلاد). وهو الآن موجودة في المتحف المصري بالقاهرة. يتكون البناء من أنورثوسيت نيس (المرتبط بالديوريت)، وهو حجر قيم، شديد الصلابة، وداكن اللون جلب 400 ميل إلى أسفل نهر النيل من المحاجر الملكية. وهذا يسلط الضوء على أهمية خفرع وقوته كحاكم. تم نحت التمثال لمعبد الوادي للملك المصري بالقرب من أبو الهول، وهو جزء من المقبرة (المدينة الجنائزية) المستخدمة في طقوس الجنازة. هذا التمثال من عصر المملكة المصرية القديمة له وظيفة مهمة في المقابر المصرية باعتباره مكان إقامة بديل للكا للملك المصري- قوة الحياة التي رافقت شخصًا مع نوع من الذات الأخرى. بعد الموت، يترك الكا الجسد في الحياة الآخرة، لكنه لا يزال بحاجة إلى مكان للراحة: التمثال.\n\n\n== وصف ==\n\nيُظهر هذا التمثال، المُصوَّر على شكل دائري (مقابل النحت البارز)، خفرع جالسًا، وهو أحد الأنواع الأساسية للصيغ المستخدمة في عصر الدولة القديمة لإظهار الشكل البشري. لعب التحنيط دورًا كبيرًا في الثقافة المصرية، وهي عملية استمرت 70 يومًا لضمان خلود الملك المصري. ابتداءً من الألفية الثالثة قبل الميلاد، في حالة تلف مومياء الملك المصري، تم إنشاء تمثال كا «لضمان خلود واستمرارية هوية المتوفى من خلال توفير مكان سكن بديل للكا».\nيجلس خفرع بصلابة على عرشه الملكي، ويحدق في المسافة. يرتدي الملك المصري غطاء رأس من الكتان يغطي معظم جبهته ويثني على كتفيه العريضين. يُصوِّر غطاء الرأس الملكي هذا الصل، أو شعار الكوبرا، على المقدمة جنبًا إلى جنب مع اللحية الملكية المستعارة المثبتة في نهاية ذقنه المحفور. يرتدي خفرع نقبة تغطي خصره، ويكشف عن الجزء العلوي من جسده المثالي والعضلات. جسد أسدين منمنمة يشكلان العرش الذي يجلس عليه خفرع، مكونًا قاعدة متينة. تنمو نباتات اللوتس (رمز مصر العليا) ونباتات البردي (رمز مصر السفلى) بين أرجل العرش، في إشارة إلى توحيد مصر العليا ومصر السفلى الذي أنهى عصر ما قبل الأسرات. يحمي الإله حورس، المُصوَّر على هيئة صقر، مؤخرة رأس خفرع بجناحيه، في إشارة أخرى إلى مصر الموحدة. إلى جانب المنظر اللافت للصقر (غير المرئي من الأمام) خلف رأس خفرع، وُضعت أقدام خفرع على منصة مسطحة، محفورة بتسعة أقواس رماية، تمثل هيمنة الملك والمملكة على قبائل العدو الأجنبية / المحلية، الأقواس التسعة.\nلا يظهر الملك المصري المتماثل أي حركة أو تغيير ، وقمع كل حركة ووقت لخلق سكون أبدي؛ إن بنائه القوي وموقفه الدائم لا يظهران أي فكرة عن الوقت - وخفر خالدة، وستظل قوته موجودة حتى في الآخرة. التمثال قائم على الصلابة والضغط مع وجود أجزاء قليلة بارزة؛ جسد خفرع الشبيه بالكتلة مرتبط بالعرش ليدوم إلى الأبد، مكونًا هيكلًا واحدًا واحدًا. ترتكز ذراعيه على فخذيه، وتواجه المشاهد مباشرة في وضع أمامي صلب. التمثال المتماثل ثنائي الجانب، الذي يرمز إلى النظام والسيطرة في الملك المصري، هو نفسه على جانبي المحور الرأسي للتمثال، ويختلف فقط في قبضة خفرع اليمنى المشدودة. كائن دائم وجزء من الحجر للحفاظ على كا له آمنًا. سوف يكون خفرع دائمًا، على الأرض وفي الآخرة. يمكن وصف تمثال الملك المصري بأنه أمامي تمامًا، وغير متحرك تمامًا ، وهادئ تمامًا: خصائص تمثال الكتلة المصرية\n\n\n== نحت ==\nمن أجل إنشاء هذا التمثال الشامل، استخدم النحات طريقة الطرح. بدأ بكتلة حجرية على شكل مكعب من الديوريت. أولاً، رسم النحات منظرين من الأمام والخلف واثنين من الجوانب الجانبية لخفرع على الوجوه الرأسية الأربعة للحجر. بعد وضع المخططات المرسومة، قام النحات بنقش الحجر الزائد من الجوانب الأربعة حتى تجتمع الخطط معًا، وتلتقي بزوايا قائمة. كانت الخطوة الأخيرة هي نحت تفاصيل محددة لجسم خفرع ووجهه، ونحت الإله الصقر حورس، وتصميمات أخرى على العرش. تتيح طريقة الطرح للنحات إنشاء مظهر يشبه الكتلة لتمثال خفرع كا، وهو معيار للنحت المصري خلال هذه الفترة الزمنية. بالإضافة إلى طريقة الطرح، تم استخدام التآكل أو الاحتكاك أو طحن السطح لإنهاء المنتج. يقف تمثال الديوريت على ارتفاع نهائي يبلغ خمسة أقدام وستة.\n\n\n== المجمع الجنائزي ==\nكان تمثال كا لخفرع، الذي كان من الممكن أن يكون موجودًا في معبد وادي خفرع، مجرد جزء واحد من نظام شديد التعقيد يستخدم في الطقوس الجنائزية المصرية. تقع المقبرة في أهرامات الجيزة، وتضم معبد وادي خفرع، ومعبد جنائزي، وأبو الهول العظيم، والجسر المؤدي إلى هرم خفرع.\nأهرامات الجيزة العظيمة، الواقعة على مشارف القاهرة الحالية، هي ثلاثة أهرامات ضخمة لثلاثة ملوك مصريين مع العديد من الأهرامات الأصغر حجمًا، وتضم مومياوات العائلة المالكة والنبلاء. من الأكبر إلى الأصغر، تعد أهرامات خوفو وخفرع ومنقرع الأكثر شهرة ومخصصة لكل إله على التوالي. تم تصميم هرم وقبر خفرع كمنزل أبدي لمومياءه، حيث كان من المفترض أن يحتفظ السرداب (غرفة الغرفة) في معبد الوادي بتمثال كا. على عكس الأهرامات السابقة، مثل هرم زوسر المدرج الذي صممه المهندس المعماري الأول المعروف إمحوتب، لم تكن أهرامات الجيزة العظيمة مبنية على هيكل المصطبة، وهو هيكل مستطيل الشكل. يُشتق السطح الجديد المائل بسلاسة للمقبرة من قاعدة مستطيلة محاذية للاتجاهات الأساسية الأربعة للبوصلة. تنتهي الجوانب الأربعة عند طرف مدبب، في إشارة إلى شعار الشمس رع، المسمى بنبن. سمحت هذه الأهرامات الرمزية لروح الملك المصري بالصعود إلى السماء باستخدام أشعة الشمس.\nبدأ موكب الجنازة الذي يحمل مومياء الملك المصري شرق نهر النيل، حيث تولد الشمس من جديد كل صباح وحيث يعيش المواطنون المصريون. كانت مومياء خفرع تعبر نهر النيل، وهو شريط الحياة الذي يفصل الشرق عن الغرب. نظرًا لأهميته ورمزه للحياة، فقد تم استخدامه كجزء من موكب لدفن الملك المصري. ثم يلتقي جثمان خفرع عند الجانب الغربي من النيل، أو أرض الموتى. تغرب الشمس كل ليلة وتموت، وهذا هو سبب تخصيص القسم الغربي من المدينة لدفن الموتى. قادتهم كل يوم تولد الشمس في الشرق وتموت ليلاً في الغرب، ومع ذلك تولد من جديد في الشرق في صباح اليوم التالي. يتوازى إيقاع المحور الأفقي المستخدم في الموكب الجنائزي مع خلود الملك المصري.\nبمجرد وصولها إلى الضفة الغربية لنهر النيل، كانت مومياء خفرع تسير على طول الجسر، أو المسار، مروراً بمعبد وادي خفرع حيث يقع تمثال خفرع المتوج. بجانب الجسر يوجد تمثال أبو الهول العظيم، وهو مخلوق برأس ملك مصري وجسم قطة منحوت من الصخور الحية / الطبيعية في المنطقة. يعتقد الكثيرون أن وجه أبو الهول هو في الواقع خفرع، مما يزيد من تكريم الملك المصري في موكب الجنازة. استمرارًا على طول الجسر، تدخل المومياء والموكب إلى معبد خفرع الجنائزي المجاور لهرم الملك المصري. هذا هو المكان الذي تم فيه تقديم القرابين للملك المصري المتوفى وأداء المزيد من الاحتفالات. ختم المومياء في قبر هرم خفرع، حيث كان جسده وكا يستريحان بسلام إلى الأبد، أكمل طقوس الجنازة.\n\n\n== المراجع ==",
    "en": "Khafre Enthroned is a Ka statue of the pharaoh Khafre, who reigned during the Fourth Dynasty of ancient Egypt. It is now located in the Egyptian Museum in Cairo. Made of anorthosite gneiss, a valuable, extremely hard, and dark stone, it was brought 1,000 km (620 mi) down the Nile River from the \"Khafre quarries\" west of Gebel el-Asr. The statue was carved for the Pharaoh's valley temple near the Great Sphinx, a part of the necropolis used in funeral rituals.\nThis sculpture, depicted in-the-round (versus relief sculpture), shows Khafre seated, one of the basic formulaic types used during the Old Kingdom to show the human figure. Mummification played a huge role in the Egyptian culture, a 70-day process to ensure immortality for the king. Starting in the 3rd millennium BCE, if the king's mummy was damaged, a ka statue was created to \"ensure immortality and permanence of the deceased's identity by providing a substitute dwelling place for the ka\".\n\nKhafre rigidly sits on his royal throne, gazing off into the distance. The pharaoh wears a linen nemes headdress, which covers most of his forehead and folds over his broad shoulders. He also wears the royal false beard attached at the end of his chiseled chin. Khafre wears a kilt covering his waist, revealing his idealized upper body and muscle definition. The Egyptian idealized portraiture is not meant to record individualized features, but instead proclaim the divine nature of Egyptian kingship. Two stylized lions' bodies form the throne Khafre sits on, creating a sturdy base. Lotus plants (symbolic of Upper Egypt) and papyrus plants (symbolic of Lower Egypt) grow between the legs of the throne, referring to the unification of Upper and Lower Egypt which ended the Egyptian predynastic period. The god Horus, depicted as a falcon, protects the backside of Khafre's head with his wings, another reference to the united Egypt. Besides the striking view of the falcon (unseen from the front) resting behind Khafre's head, Khafre's feet are emplaced upon a flat platform, engraved with nine archery bows, representing the king's and kingdom's dominance over foreign/domestic enemy tribes, the nine bows.\nThe symmetrical king shows no movement or change, suppressing all motion and time to create an eternal stillness; his strong build and permanent stance demonstrate no notion of time—Khafre is timeless, and his power will exist even in the afterlife. The statue is based upon compactness and solidity with few projecting parts; Khafre's block-like body is attached to the throne to last for eternity, creating one single structure. His arms rest on his thighs, directly facing the viewer in a rigid, frontal pose. The bilaterally symmetric statue, symbolizing order and control in the pharaoh, is the same on either side of the vertical axis of the statue, only differing in Khafre's clenched right fist. The tight profile and block-like aspect represent Khafre as a permanent being and part of the stone to keep his ka safe. Khafre will always exist, on earth and in the afterlife. The pharaoh's sculpture can be described as absolutely frontal, utterly immobile, and perfectly calm: the characteristics of Egyptian block statue.\nThe diorite statue stands at a final height of five foot six.\n\n\n== References ==\n\n\n== Further reading ==\nBorchardt, Ludwig (1911). Statuen und Statuetten von Königen und Privatleuten: im Museum von Kairo [Statues and statuettes of kings and private people in the museum of Cairo] (in German). pp. 9–19. doi:10.11588/diglit.34230#0019.\nHölscher, Uvo (1912). \"Die Statuenfragmente aus dem alten Reich\" [The statue fragments of the Old Kingdom]. Das Grabdenkmal des Königs Chephren (in German). pp. 89–104.",
    "ar_intro": "خفرع متوج هو تمثال جنائزي للملك المصري خفرع، الذي حكم خلال الأسرة المصرية الرابعة. وهو الآن موجودة في المتحف المصري بالقاهرة. يتكون البناء من أنورثوسيت نيس ، وهو حجر قيم، شديد الصلابة، وداكن اللون جلب 400 ميل إلى أسفل نهر النيل من المحاجر الملكية. وهذا يسلط الضوء على أهمية خفرع وقوته كحاكم. تم نحت التمثال لمعبد الوادي للملك المصري بالقرب من أبو الهول، وهو جزء من المقبرة المستخدمة في طقوس الجنازة. هذا التمثال من عصر المملكة المصرية القديمة له وظيفة مهمة في المقابر المصرية باعتباره مكان إقامة بديل للكا للملك المصري- قوة الحياة التي رافقت شخصًا مع نوع من الذات الأخرى. بعد الموت، يترك الكا الجسد في الحياة الآخرة، لكنه لا يزال بحاجة إلى مكان للراحة: التمثال.",
    "en_intro": "Khafre Enthroned is a Ka statue of the pharaoh Khafre, who reigned during the Fourth Dynasty of ancient Egypt. It is now located in the Egyptian Museum in Cairo. Made of anorthosite gneiss, a valuable, extremely hard, and dark stone, it was brought 1,000 km (620 mi) down the Nile River from the \"Khafre quarries\" west of Gebel el-Asr. The statue was carved for the Pharaoh's valley temple near the Great Sphinx, a part of the necropolis used in funeral rituals."
  },
  "images": [
    {
      "filename": "KHAFRE_ENTHRONED_01.jpg",
      "source": "wikimedia_commons",
      "source_url": "https://commons.wikimedia.org/wiki/File:Kairo_Museum_Sitzstatue_Chephren_06.jpg",
      "credit": "Olaf Tausch",
      "license": "CC BY 3.0",
      "license_url": "https://creativecommons.org/licenses/by/3.0",
      "width": 2626,
      "height": 3499,
      "is_primary": true,
      "caption_en": "Sitzstatue des Königs Chephren der 4. altägyptischen Dynastie, ausgestellt im Ägyptischen Museum in Kairo, Ägypten",
      "object_name": "Kairo Museum Sitzstatue Chephren 06",
      "original_filename": "Kairo_Museum_Sitzstatue_Chephren_06.jpg"
    },
    {
      "filename": "KHAFRE_ENTHRONED_02.jpg",
      "source": "wikimedia_commons",
      "source_url": "https://commons.wikimedia.org/wiki/File:Chephren_CG_14.jpg",
      "credit": "Ludwig Borchardt (1863-1938)",
      "license": "Public domain",
      "license_url": "",
      "width": 423,
      "height": 593,
      "is_primary": false,
      "caption_en": "Statue of Khafra from his valley temple at Giza, now in the Egyptian Museum, Cairo (CG 14)",
      "object_name": "Chephren CG 14",
      "original_filename": "Chephren_CG_14.jpg"
    },
    {
      "filename": "KHAFRE_ENTHRONED_03.jpg",
      "source": "wikimedia_commons",
      "source_url": "https://commons.wikimedia.org/wiki/File:Khafre_Enthroned%2C_three-quarter_view.JPG",
      "credit": "A. Parrot",
      "license": "CC0",
      "license_url": "http://creativecommons.org/publicdomain/zero/1.0/deed.en",
      "width": 2248,
      "height": 3543,
      "is_primary": false,
      "caption_en": "The statue of Khafre from his valley temple at Giza, now in the Egyptian Museum of Antiquities in Cairo. A figure of a falcon—the god Horus—extends his wings around the king's head. Fourth Dynasty, 26th century BC.",
      "object_name": "Khafre Enthroned, three-quarter view",
      "original_filename": "Khafre_Enthroned,_three-quarter_view.JPG"
    },
    {
      "filename": "KHAFRE_ENTHRONED_04.jpg",
      "source": "wikimedia_commons",
      "source_url": "https://commons.wikimedia.org/wiki/File:Khafre_statue.jpg",
      "credit": "Jon Bodsworth",
      "license": "Copyrighted free use",
      "license_url": "",
      "width": 500,
      "height": 667,
      "is_primary": false,
      "caption_en": "RR²",
      "object_name": "Khafre statue",
      "original_filename": "Khafre_statue.jpg"
    },
    {
      "filename": "KHAFRE_ENTHRONED_05.jpg",
      "source": "wikimedia_commons",
      "source_url": "https://commons.wikimedia.org/wiki/File:Khephren%2BHorus.jpg",
      "credit": "Soutekh67",
      "license": "CC BY-SA 4.0",
      "license_url": "https://creativecommons.org/licenses/by-sa/4.0",
      "width": 349,
      "height": 303,
      "is_primary": false,
      "caption_en": "Gros plan sur une statue assise de Khephren. Le dieu Horus protégeant la tête du pharaon. IVe dynastie. Musée égyptien du Caire.",
      "object_name": "Khephren+Horus",
      "original_filename": "Khephren+Horus.jpg"
    }
  ],
  "sources": [
    {
      "type": "wikipedia_en",
      "url": "https://en.wikipedia.org/wiki/Khafre_Enthroned",
      "title": "Khafre Enthroned",
      "license": "CC-BY-SA-4.0"
    },
    {
      "type": "wikipedia_ar",
      "url": "https://ar.wikipedia.org/wiki/%D8%AE%D9%81%D8%B1%D8%B9_%D9%85%D8%AA%D9%88%D8%AC",
      "title": "خفرع متوج",
      "license": "CC-BY-SA-4.0"
    }
  ],
  "tags": [
    "1860 archaeological discoveries",
    "26th-century bc works",
    "all articles needing additional references",
    "all articles with style issues",
    "all articles with unsourced statements",
    "archaeological discoveries in egypt",
    "articles needing additional references from october 2022",
    "articles with multiple maintenance issues",
    "articles with short description",
    "articles with unsourced statements from march 2021",
    "commons category link is on wikidata",
    "cs1 german-language sources (de)",
    "egyptian museum",
    "khafre",
    "pages using infobox mapframe with missing coordinates",
    "sculptures of ancient egypt",
    "short description is different from wikidata",
    "wikipedia articles with style issues from october 2022"
  ],
  "related_ids": [
    "MET_543896",
    "NARMER_PALETTE",
    "SEATED_SCRIBE",
    "APIS_BULL",
    "PHILAE_TEMPLE",
    "DEIR_EL_BAHARI",
    "ABYDOS",
    "CANOPUS_DECREE"
  ],
  "qa_pairs_ar": [
    {
      "q": "ما هي خفرع متوج؟",
      "a": "خفرع متوج هو تمثال جنائزي للملك المصري خفرع، الذي حكم خلال الأسرة المصرية الرابعة (حوالي 2570 قبل الميلاد).",
      "evidence": "description.ar_intro",
      "type": "identity"
    },
    {
      "q": "أين توجد خفرع متوج حاليًا؟",
      "a": "تُحفظ خفرع متوج في المتحف المصري في القاهرة.",
      "evidence": "current_location",
      "type": "location"
    },
    {
      "q": "من أي مادة صُنعت خفرع متوج؟",
      "a": "صُنعت خفرع متوج من Anorthosite gneiss.",
      "evidence": "material",
      "type": "material"
    },
    {
      "q": "متى اكتُشفت خفرع متوج؟",
      "a": "اكتُشفت خفرع متوج عام 1860.",
      "evidence": "discovery.year",
      "type": "discovery"
    },
    {
      "q": "من أين أُحضرت خفرع متوج؟",
      "a": "أُحضرت خفرع متوج من Giza, Giza Governorate, Egypt.",
      "evidence": "provenance",
      "type": "provenance"
    },
    {
      "q": "اعطني نبذة عن خفرع متوج.",
      "a": "خفرع متوج هو تمثال جنائزي للملك المصري خفرع، الذي حكم خلال الأسرة المصرية الرابعة (حوالي 2570 قبل الميلاد). وهو الآن موجودة في المتحف المصري بالقاهرة. يتكون البناء من أنورثوسيت نيس (المرتبط بالديوريت)، وهو حجر قيم، شديد الصلابة، وداكن اللون جلب 400 ميل إلى أسفل نهر النيل من المحاجر الملكية. وهذا يسلط الضوء على أهمية خفرع وقوته كحاكم. تم نحت التمثال لمعبد الوادي للملك المصري بالقرب من أبو الهول، وهو جزء من المقبرة (المدينة الجنائزية) المستخدمة في طقوس الجنازة. هذا التمثال من عصر المملكة المصرية القديمة له وظيفة مهمة في المقابر المصرية باعتباره مكان إقامة بديل للكا للملك المصري- قوة الحياة التي ...",
      "evidence": "description.ar",
      "type": "summary"
    }
  ],
  "highlight": true
}